UART + Motor Control/tenth_timer.vhd
library ieee;
use ieee.std_logic_1164.all;
use ieee.numeric_std.all;

entity tenth_timer is
    port (
           clk : in std_logic;
	   tenth_tick : out std_logic
    );
end tenth_timer;

architecture behavior of tenth_timer is

signal TENTH_DELAY : unsigned(23 downto 0) := x"989680"; 
signal tenth_counter : unsigned(23 downto 0) := (others => '0');
signal reset : std_logic := '0';
signal tick1, tick2 : std_logic := '0';

begin

	process (clk)
        	begin
    		if rising_edge(clk) then
			if (reset = '1') then
				tenth_counter <= (others => '0');
			else
				tenth_counter <= tenth_counter + 1;
			end if;
		end if;
	end process;

	process (clk)
        	begin
    		if rising_edge(clk) then
			if (tenth_counter = x"98967F") then
				reset <= '1';
			else
				reset <= '0';
			end if;
		end if;
	end process;	
	
	process (clk)
        	begin
    		if rising_edge(clk) then 
			tick1 <= reset;
		end if;
	end process;

	process (clk)
        	begin
    		if rising_edge(clk) then 
			tick2 <= tick1;
		end if;
	end process;

	tenth_tick <= tick1 AND (NOT tick2);					

end behavior;

UART + Motor Control/tenth_timer_tb.vhd
library IEEE;
use IEEE.std_logic_1164.all;
use ieee.numeric_std.all;

entity tenth_timer_tb is
end tenth_timer_tb;

architecture testbench of tenth_timer_tb is
    constant num_cycles : integer := 50000;
    signal clk : std_logic := '1';
    signal tenth_tick : std_logic;
    component tenth_timer is
        port (
            	clk : in std_logic;
		tenth_tick : out std_logic
	     );
    end component;

begin
	dut : tenth_timer port map(clk, tenth_tick);
    process
    begin
    
    report "* START OF TESTBENCH *";

    for i in 1 to num_cycles loop
      clk <= not clk;
      wait for 5 ns;
      clk <= not clk;
      wait for 5 ns;
      -- clock period = 10 ns
    end loop;

    report "* END OF TESTBENCH *";
    wait;
    end process;

end testbench;

UART + Motor Control/tenth_timer_tp.vcd
$date
  Thu Jan 28 17:03:46 2021
$end
$version
  GHDL v0
$end
$timescale
  1 fs
$end
$scope module standard $end
$upscope $end
$scope module std_logic_1164 $end
$upscope $end
$scope module numeric_std $end
$upscope $end
$scope module tenth_timer_tb $end
$var reg 1 ! clk $end
$var reg 1 " tenth_tick $end
$scope module dut $end
$var reg 1 # clk $end
$var reg 1 $ tenth_tick $end
$var reg 24 % tenth_delay[23:0] $end
$var reg 24 & tenth_counter[23:0] $end
$var reg 1 ' reset $end
$var reg 1 ( tick1 $end
$var reg 1 ) tick2 $end
$upscope $end
$upscope $end
$enddefinitions $end
#0
0!
0"
0#
0$
b100110001001011010000000 %
b000000000000000000000000 &
0'
0(
0)
#5000000
1!
1#
b000000000000000000000001 &
#10000000
0!
0#
#15000000
1!
1#
b000000000000000000000010 &
#20000000
0!
0#
#25000000
1!
1#
b000000000000000000000011 &
#30000000
0!
0#
#35000000
1!
1#
b000000000000000000000100 &
#40000000
0!
0#
#45000000
1!
1#
b000000000000000000000101 &
#50000000
0!
0#
#55000000
1!
1#
b000000000000000000000110 &
#60000000
0!
0#
#65000000
1!
1#
b000000000000000000000111 &
#70000000
0!
0#
#75000000
1!
1#
b000000000000000000001000 &
#80000000
0!
0#
#85000000
1!
1#
b000000000000000000001001 &
#90000000
0!
0#
#95000000
1!
1#
b000000000000000000001010 &
1'
#100000000
0!
0#
#105000000
1!
1"
1#
1$
b000000000000000000000000 &
0'
1(
#110000000
0!
0#
#115000000
1!
0"
1#
0$
b000000000000000000000001 &
0(
1)
#120000000
0!
0#
#125000000
1!
1#
b000000000000000000000010 &
0)
#130000000
0!
0#
#135000000
1!
1#
b000000000000000000000011 &
#140000000
0!
0#
#145000000
1!
1#
b000000000000000000000100 &
#150000000
0!
0#
#155000000
1!
1#
b000000000000000000000101 &
#160000000
0!
0#
#165000000
1!
1#
b000000000000000000000110 &
#170000000
0!
0#
#175000000
1!
1#
b000000000000000000000111 &
#180000000
0!
0#
#185000000
1!
1#
b000000000000000000001000 &
#190000000
0!
0#
#195000000
1!
1#
b000000000000000000001001 &
#200000000
0!
0#
#205000000
1!
1#
b000000000000000000001010 &
1'
#210000000
0!
0#
#215000000
1!
1"
1#
1$
b000000000000000000000000 &
0'
1(
#220000000
0!
0#
#225000000
1!
0"
1#
0$
b000000000000000000000001 &
0(
1)
#230000000
0!
0#
#235000000
1!
1#
b000000000000000000000010 &
0)
#240000000
0!
0#
#245000000
1!
1#
b000000000000000000000011 &
#250000000
0!
0#
#255000000
1!
1#
b000000000000000000000100 &
#260000000
0!
0#
#265000000
1!
1#
b000000000000000000000101 &
#270000000
0!
0#
#275000000
1!
1#
b000000000000000000000110 &
#280000000
0!
0#
#285000000
1!
1#
b000000000000000000000111 &
#290000000
0!
0#
#295000000
1!
1#
b000000000000000000001000 &
#300000000
0!
0#
#305000000
1!
1#
b000000000000000000001001 &
#310000000
0!
0#
#315000000
1!
1#
b000000000000000000001010 &
1'
#320000000
0!
0#
#325000000
1!
1"
1#
1$
b000000000000000000000000 &
0'
1(
#330000000
0!
0#
#335000000
1!
0"
1#
0$
b000000000000000000000001 &
0(
1)
#340000000
0!
0#
#345000000
1!
1#
b000000000000000000000010 &
0)
#350000000
0!
0#
#355000000
1!
1#
b000000000000000000000011 &
#360000000
0!
0#
#365000000
1!
1#
b000000000000000000000100 &
#370000000
0!
0#
#375000000
1!
1#
b000000000000000000000101 &
#380000000
0!
0#
#385000000
1!
1#
b000000000000000000000110 &
#390000000
0!
0#
#395000000
1!
1#
b000000000000000000000111 &
#400000000
0!
0#
#405000000
1!
1#
b000000000000000000001000 &
#410000000
0!
0#
#415000000
1!
1#
b000000000000000000001001 &
#420000000
0!
0#
#425000000
1!
1#
b000000000000000000001010 &
1'
#430000000
0!
0#
#435000000
1!
1"
1#
1$
b000000000000000000000000 &
0'
1(
#440000000
0!
0#
#445000000
1!
0"
1#
0$
b000000000000000000000001 &
0(
1)
#450000000
0!
0#
#455000000
1!
1#
b000000000000000000000010 &
0)
#460000000
0!
0#
#465000000
1!
1#
b000000000000000000000011 &
#470000000
0!
0#
#475000000
1!
1#
b000000000000000000000100 &
#480000000
0!
0#
#485000000
1!
1#
b000000000000000000000101 &
#490000000
0!
0#
#495000000
1!
1#
b000000000000000000000110 &
#500000000
0!
0#
#505000000
1!
1#
b000000000000000000000111 &
#510000000
0!
0#
#515000000
1!
1#
b000000000000000000001000 &
#520000000
0!
0#
#525000000
1!
1#
b000000000000000000001001 &
#530000000
0!
0#
#535000000
1!
1#
b000000000000000000001010 &
1'
#540000000
0!
0#
#545000000
1!
1"
1#
1$
b000000000000000000000000 &
0'
1(
#550000000
0!
0#
#555000000
1!
0"
1#
0$
b000000000000000000000001 &
0(
1)
#560000000
0!
0#
#565000000
1!
1#
b000000000000000000000010 &
0)
#570000000
0!
0#
#575000000
1!
1#
b000000000000000000000011 &
#580000000
0!
0#
#585000000
1!
1#
b000000000000000000000100 &
#590000000
0!
0#
#595000000
1!
1#
b000000000000000000000101 &
#600000000
0!
0#
#605000000
1!
1#
b000000000000000000000110 &
#610000000
0!
0#
#615000000
1!
1#
b000000000000000000000111 &
#620000000
0!
0#
#625000000
1!
1#
b000000000000000000001000 &
#630000000
0!
0#
#635000000
1!
1#
b000000000000000000001001 &
#640000000
0!
0#
#645000000
1!
1#
b000000000000000000001010 &
1'
#650000000
0!
0#
#655000000
1!
1"
1#
1$
b000000000000000000000000 &
0'
1(
#660000000
0!
0#
#665000000
1!
0"
1#
0$
b000000000000000000000001 &
0(
1)
#670000000
0!
0#
#675000000
1!
1#
b000000000000000000000010 &
0)
#680000000
0!
0#
#685000000
1!
1#
b000000000000000000000011 &
#690000000
0!
0#
#695000000
1!
1#
b000000000000000000000100 &
#700000000
0!
0#
#705000000
1!
1#
b000000000000000000000101 &
#710000000
0!
0#
#715000000
1!
1#
b000000000000000000000110 &
#720000000
0!
0#
#725000000
1!
1#
b000000000000000000000111 &
#730000000
0!
0#
#735000000
1!
1#
b000000000000000000001000 &
#740000000
0!
0#
#745000000
1!
1#
b000000000000000000001001 &
#750000000
0!
0#
#755000000
1!
1#
b000000000000000000001010 &
1'
#760000000
0!
0#
#765000000
1!
1"
1#
1$
b000000000000000000000000 &
0'
1(
#770000000
0!
0#
#775000000
1!
0"
1#
0$
b000000000000000000000001 &
0(
1)
#780000000
0!
0#
#785000000
1!
1#
b000000000000000000000010 &
0)
#790000000
0!
0#
#795000000
1!
1#
b000000000000000000000011 &
#800000000
0!
0#
#805000000
1!
1#
b000000000000000000000100 &
#810000000
0!
0#
#815000000
1!
1#
b000000000000000000000101 &
#820000000
0!
0#
#825000000
1!
1#
b000000000000000000000110 &
#830000000
0!
0#
#835000000
1!
1#
b000000000000000000000111 &
#840000000
0!
0#
#845000000
1!
1#
b000000000000000000001000 &
#850000000
0!
0#
#855000000
1!
1#
b000000000000000000001001 &
#860000000
0!
0#
#865000000
1!
1#
b000000000000000000001010 &
1'
#870000000
0!
0#
#875000000
1!
1"
1#
1$
b000000000000000000000000 &
0'
1(
#880000000
0!
0#
#885000000
1!
0"
1#
0$
b000000000000000000000001 &
0(
1)
#890000000
0!
0#
#895000000
1!
1#
b000000000000000000000010 &
0)
#900000000
0!
0#
#905000000
1!
1#
b000000000000000000000011 &
#910000000
0!
0#
#915000000
1!
1#
b000000000000000000000100 &
#920000000
0!
0#
#925000000
1!
1#
b000000000000000000000101 &
#930000000
0!
0#
#935000000
1!
1#
b000000000000000000000110 &
#940000000
0!
0#
#945000000
1!
1#
b000000000000000000000111 &
#950000000
0!
0#
#955000000
1!
1#
b000000000000000000001000 &
#960000000
0!
0#
#965000000
1!
1#
b000000000000000000001001 &
#970000000
0!
0#
#975000000
1!
1#
b000000000000000000001010 &
1'
#980000000
0!
0#
#985000000
1!
1"
1#
1$
b000000000000000000000000 &
0'
1(
#990000000
0!
0#
#995000000
1!
0"
1#
0$
b000000000000000000000001 &
0(
1)
#1000000000
0!
0#
#1005000000
1!
1#
b000000000000000000000010 &
0)
#1010000000
0!
0#
#1015000000
1!
1#
b000000000000000000000011 &
#1020000000
0!
0#
#1025000000
1!
1#
b000000000000000000000100 &
#1030000000
0!
0#
#1035000000
1!
1#
b000000000000000000000101 &
#1040000000
0!
0#
#1045000000
1!
1#
b000000000000000000000110 &
#1050000000
0!
0#
#1055000000
1!
1#
b000000000000000000000111 &
#1060000000
0!
0#
#1065000000
1!
1#
b000000000000000000001000 &
#1070000000
0!
0#
#1075000000
1!
1#
b000000000000000000001001 &
#1080000000
0!
0#
#1085000000
1!
1#
b000000000000000000001010 &
1'
#1090000000
0!
0#
#1095000000
1!
1"
1#
1$
b000000000000000000000000 &
0'
1(
#1100000000
0!
0#
#1105000000
1!
0"
1#
0$
b000000000000000000000001 &
0(
1)
#1110000000
0!
0#
#1115000000
1!
1#
b000000000000000000000010 &
0)
#1120000000
0!
0#
#1125000000
1!
1#
b000000000000000000000011 &
#1130000000
0!
0#
#1135000000
1!
1#
b000000000000000000000100 &
#1140000000
0!
0#
#1145000000
1!
1#
b000000000000000000000101 &
#1150000000
0!
0#
#1155000000
1!
1#
b000000000000000000000110 &
#1160000000
0!
0#
#1165000000
1!
1#
b000000000000000000000111 &
#1170000000
0!
0#
#1175000000
1!
1#
b000000000000000000001000 &
#1180000000
0!
0#
#1185000000
1!
1#
b000000000000000000001001 &
#1190000000
0!
0#
#1195000000
1!
1#
b000000000000000000001010 &
1'
#1200000000
0!
0#
#1205000000
1!
1"
1#
1$
b000000000000000000000000 &
0'
1(
#1210000000
0!
0#
#1215000000
1!
0"
1#
0$
b000000000000000000000001 &
0(
1)
#1220000000
0!
0#
#1225000000
1!
1#
b000000000000000000000010 &
0)
#1230000000
0!
0#
#1235000000
1!
1#
b000000000000000000000011 &
#1240000000
0!
0#
#1245000000
1!
1#
b000000000000000000000100 &
#1250000000
0!
0#
#1255000000
1!
1#
b000000000000000000000101 &
#1260000000
0!
0#
#1265000000
1!
1#
b000000000000000000000110 &
#1270000000
0!
0#
#1275000000
1!
1#
b000000000000000000000111 &
#1280000000
0!
0#
#1285000000
1!
1#
b000000000000000000001000 &
#1290000000
0!
0#
#1295000000
1!
1#
b000000000000000000001001 &
#1300000000
0!
0#
#1305000000
1!
1#
b000000000000000000001010 &
1'
#1310000000
0!
0#
#1315000000
1!
1"
1#
1$
b000000000000000000000000 &
0'
1(
#1320000000
0!
0#
#1325000000
1!
0"
1#
0$
b000000000000000000000001 &
0(
1)
#1330000000
0!
0#
#1335000000
1!
1#
b000000000000000000000010 &
0)
#1340000000
0!
0#
#1345000000
1!
1#
b000000000000000000000011 &
#1350000000
0!
0#
#1355000000
1!
1#
b000000000000000000000100 &
#1360000000
0!
0#
#1365000000
1!
1#
b000000000000000000000101 &
#1370000000
0!
0#
#1375000000
1!
1#
b000000000000000000000110 &
#1380000000
0!
0#
#1385000000
1!
1#
b000000000000000000000111 &
#1390000000
0!
0#
#1395000000
1!
1#
b000000000000000000001000 &
#1400000000
0!
0#
#1405000000
1!
1#
b000000000000000000001001 &
#1410000000
0!
0#
#1415000000
1!
1#
b000000000000000000001010 &
1'
#1420000000
0!
0#
#1425000000
1!
1"
1#
1$
b000000000000000000000000 &
0'
1(
#1430000000
0!
0#
#1435000000
1!
0"
1#
0$
b000000000000000000000001 &
0(
1)
#1440000000
0!
0#
#1445000000
1!
1#
b000000000000000000000010 &
0)
#1450000000
0!
0#
#1455000000
1!
1#
b000000000000000000000011 &
#1460000000
0!
0#
#1465000000
1!
1#
b000000000000000000000100 &
#1470000000
0!
0#
#1475000000
1!
1#
b000000000000000000000101 &
#1480000000
0!
0#
#1485000000
1!
1#
b000000000000000000000110 &
#1490000000
0!
0#
#1495000000
1!
1#
b000000000000000000000111 &
#1500000000
0!
0#
#1505000000
1!
1#
b000000000000000000001000 &
#1510000000
0!
0#
#1515000000
1!
1#
b000000000000000000001001 &
#1520000000
0!
0#
#1525000000
1!
1#
b000000000000000000001010 &
1'
#1530000000
0!
0#
#1535000000
1!
1"
1#
1$
b000000000000000000000000 &
0'
1(
#1540000000
0!
0#
#1545000000
1!
0"
1#
0$
b000000000000000000000001 &
0(
1)
#1550000000
0!
0#
#1555000000
1!
1#
b000000000000000000000010 &
0)
#1560000000
0!
0#
#1565000000
1!
1#
b000000000000000000000011 &
#1570000000
0!
0#
#1575000000
1!
1#
b000000000000000000000100 &
#1580000000
0!
0#
#1585000000
1!
1#
b000000000000000000000101 &
#1590000000
0!
0#
#1595000000
1!
1#
b000000000000000000000110 &
#1600000000
0!
0#
#1605000000
1!
1#
b000000000000000000000111 &
#1610000000
0!
0#
#1615000000
1!
1#
b000000000000000000001000 &
#1620000000
0!
0#
#1625000000
1!
1#
b000000000000000000001001 &
#1630000000
0!
0#
#1635000000
1!
1#
b000000000000000000001010 &
1'
#1640000000
0!
0#
#1645000000
1!
1"
1#
1$
b000000000000000000000000 &
0'
1(
#1650000000
0!
0#
#1655000000
1!
0"
1#
0$
b000000000000000000000001 &
0(
1)
#1660000000
0!
0#
#1665000000
1!
1#
b000000000000000000000010 &
0)
#1670000000
0!
0#
#1675000000
1!
1#
b000000000000000000000011 &
#1680000000
0!
0#
#1685000000
1!
1#
b000000000000000000000100 &
#1690000000
0!
0#
#1695000000
1!
1#
b000000000000000000000101 &
#1700000000
0!
0#
#1705000000
1!
1#
b000000000000000000000110 &
#1710000000
0!
0#
#1715000000
1!
1#
b000000000000000000000111 &
#1720000000
0!
0#
#1725000000
1!
1#
b000000000000000000001000 &
#1730000000
0!
0#
#1735000000
1!
1#
b000000000000000000001001 &
#1740000000
0!
0#
#1745000000
1!
1#
b000000000000000000001010 &
1'
#1750000000
0!
0#
#1755000000
1!
1"
1#
1$
b000000000000000000000000 &
0'
1(
#1760000000
0!
0#
#1765000000
1!
0"
1#
0$
b000000000000000000000001 &
0(
1)
#1770000000
0!
0#
#1775000000
1!
1#
b000000000000000000000010 &
0)
#1780000000
0!
0#
#1785000000
1!
1#
b000000000000000000000011 &
#1790000000
0!
0#
#1795000000
1!
1#
b000000000000000000000100 &
#1800000000
0!
0#
#1805000000
1!
1#
b000000000000000000000101 &
#1810000000
0!
0#
#1815000000
1!
1#
b000000000000000000000110 &
#1820000000
0!
0#
#1825000000
1!
1#
b000000000000000000000111 &
#1830000000
0!
0#
#1835000000
1!
1#
b000000000000000000001000 &
#1840000000
0!
0#
#1845000000
1!
1#
b000000000000000000001001 &
#1850000000
0!
0#
#1855000000
1!
1#
b000000000000000000001010 &
1'
#1860000000
0!
0#
#1865000000
1!
1"
1#
1$
b000000000000000000000000 &
0'
1(
#1870000000
0!
0#
#1875000000
1!
0"
1#
0$
b000000000000000000000001 &
0(
1)
#1880000000
0!
0#
#1885000000
1!
1#
b000000000000000000000010 &
0)
#1890000000
0!
0#
#1895000000
1!
1#
b000000000000000000000011 &
#1900000000
0!
0#
#1905000000
1!
1#
b000000000000000000000100 &
#1910000000
0!
0#
#1915000000
1!
1#
b000000000000000000000101 &
#1920000000
0!
0#
#1925000000
1!
1#
b000000000000000000000110 &
#1930000000
0!
0#
#1935000000
1!
1#
b000000000000000000000111 &
#1940000000
0!
0#
#1945000000
1!
1#
b000000000000000000001000 &
#1950000000
0!
0#
#1955000000
1!
1#
b000000000000000000001001 &
#1960000000
0!
0#
#1965000000
1!
1#
b000000000000000000001010 &
1'
#1970000000
0!
0#
#1975000000
1!
1"
1#
1$
b000000000000000000000000 &
0'
1(
#1980000000
0!
0#
#1985000000
1!
0"
1#
0$
b000000000000000000000001 &
0(
1)
#1990000000
0!
0#
#1995000000
1!
1#
b000000000000000000000010 &
0)
#2000000000
0!
0#
#2005000000
1!
1#
b000000000000000000000011 &
#2010000000
0!
0#
#2015000000
1!
1#
b000000000000000000000100 &
#2020000000
0!
0#
#2025000000
1!
1#
b000000000000000000000101 &
#2030000000
0!
0#
#2035000000
1!
1#
b000000000000000000000110 &
#2040000000
0!
0#
#2045000000
1!
1#
b000000000000000000000111 &
#2050000000
0!
0#
#2055000000
1!
1#
b000000000000000000001000 &
#2060000000
0!
0#
#2065000000
1!
1#
b000000000000000000001001 &
#2070000000
0!
0#
#2075000000
1!
1#
b000000000000000000001010 &
1'
#2080000000
0!
0#
#2085000000
1!
1"
1#
1$
b000000000000000000000000 &
0'
1(
#2090000000
0!
0#
#2095000000
1!
0"
1#
0$
b000000000000000000000001 &
0(
1)
#2100000000
0!
0#
#2105000000
1!
1#
b000000000000000000000010 &
0)
#2110000000
0!
0#
#2115000000
1!
1#
b000000000000000000000011 &
#2120000000
0!
0#
#2125000000
1!
1#
b000000000000000000000100 &
#2130000000
0!
0#
#2135000000
1!
1#
b000000000000000000000101 &
#2140000000
0!
0#
#2145000000
1!
1#
b000000000000000000000110 &
#2150000000
0!
0#
#2155000000
1!
1#
b000000000000000000000111 &
#2160000000
0!
0#
#2165000000
1!
1#
b000000000000000000001000 &
#2170000000
0!
0#
#2175000000
1!
1#
b000000000000000000001001 &
#2180000000
0!
0#
#2185000000
1!
1#
b000000000000000000001010 &
1'
#2190000000
0!
0#
#2195000000
1!
1"
1#
1$
b000000000000000000000000 &
0'
1(
#2200000000
0!
0#
#2205000000
1!
0"
1#
0$
b000000000000000000000001 &
0(
1)
#2210000000
0!
0#
#2215000000
1!
1#
b000000000000000000000010 &
0)
#2220000000
0!
0#
#2225000000
1!
1#
b000000000000000000000011 &
#2230000000
0!
0#
#2235000000
1!
1#
b000000000000000000000100 &
#2240000000
0!
0#
#2245000000
1!
1#
b000000000000000000000101 &
#2250000000
0!
0#
#2255000000
1!
1#
b000000000000000000000110 &
#2260000000
0!
0#
#2265000000
1!
1#
b000000000000000000000111 &
#2270000000
0!
0#
#2275000000
1!
1#
b000000000000000000001000 &
#2280000000
0!
0#
#2285000000
1!
1#
b000000000000000000001001 &
#2290000000
0!
0#
#2295000000
1!
1#
b000000000000000000001010 &
1'
#2300000000
0!
0#
#2305000000
1!
1"
1#
1$
b000000000000000000000000 &
0'
1(
#2310000000
0!
0#
#2315000000
1!
0"
1#
0$
b000000000000000000000001 &
0(
1)
#2320000000
0!
0#
#2325000000
1!
1#
b000000000000000000000010 &
0)
#2330000000
0!
0#
#2335000000
1!
1#
b000000000000000000000011 &
#2340000000
0!
0#
#2345000000
1!
1#
b000000000000000000000100 &
#2350000000
0!
0#
#2355000000
1!
1#
b000000000000000000000101 &
#2360000000
0!
0#
#2365000000
1!
1#
b000000000000000000000110 &
#2370000000
0!
0#
#2375000000
1!
1#
b000000000000000000000111 &
#2380000000
0!
0#
#2385000000
1!
1#
b000000000000000000001000 &
#2390000000
0!
0#
#2395000000
1!
1#
b000000000000000000001001 &
#2400000000
0!
0#
#2405000000
1!
1#
b000000000000000000001010 &
1'
#2410000000
0!
0#
#2415000000
1!
1"
1#
1$
b000000000000000000000000 &
0'
1(
#2420000000
0!
0#
#2425000000
1!
0"
1#
0$
b000000000000000000000001 &
0(
1)
#2430000000
0!
0#
#2435000000
1!
1#
b000000000000000000000010 &
0)
#2440000000
0!
0#
#2445000000
1!
1#
b000000000000000000000011 &
#2450000000
0!
0#
#2455000000
1!
1#
b000000000000000000000100 &
#2460000000
0!
0#
#2465000000
1!
1#
b000000000000000000000101 &
#2470000000
0!
0#
#2475000000
1!
1#
b000000000000000000000110 &
#2480000000
0!
0#
#2485000000
1!
1#
b000000000000000000000111 &
#2490000000
0!
0#
#2495000000
1!
1#
b000000000000000000001000 &
#2500000000
0!
0#
#2505000000
1!
1#
b000000000000000000001001 &
#2510000000
0!
0#
#2515000000
1!
1#
b000000000000000000001010 &
1'
#2520000000
0!
0#
#2525000000
1!
1"
1#
1$
b000000000000000000000000 &
0'
1(
#2530000000
0!
0#
#2535000000
1!
0"
1#
0$
b000000000000000000000001 &
0(
1)
#2540000000
0!
0#
#2545000000
1!
1#
b000000000000000000000010 &
0)
#2550000000
0!
0#
#2555000000
1!
1#
b000000000000000000000011 &
#2560000000
0!
0#
#2565000000
1!
1#
b000000000000000000000100 &
#2570000000
0!
0#
#2575000000
1!
1#
b000000000000000000000101 &
#2580000000
0!
0#
#2585000000
1!
1#
b000000000000000000000110 &
#2590000000
0!
0#
#2595000000
1!
1#
b000000000000000000000111 &
#2600000000
0!
0#
#2605000000
1!
1#
b000000000000000000001000 &
#2610000000
0!
0#
#2615000000
1!
1#
b000000000000000000001001 &
#2620000000
0!
0#
#2625000000
1!
1#
b000000000000000000001010 &
1'
#2630000000
0!
0#
#2635000000
1!
1"
1#
1$
b000000000000000000000000 &
0'
1(
#2640000000
0!
0#
#2645000000
1!
0"
1#
0$
b000000000000000000000001 &
0(
1)
#2650000000
0!
0#
#2655000000
1!
1#
b000000000000000000000010 &
0)
#2660000000
0!
0#
#2665000000
1!
1#
b000000000000000000000011 &
#2670000000
0!
0#
#2675000000
1!
1#
b000000000000000000000100 &
#2680000000
0!
0#
#2685000000
1!
1#
b000000000000000000000101 &
#2690000000
0!
0#
#2695000000
1!
1#
b000000000000000000000110 &
#2700000000
0!
0#
#2705000000
1!
1#
b000000000000000000000111 &
#2710000000
0!
0#
#2715000000
1!
1#
b000000000000000000001000 &
#2720000000
0!
0#
#2725000000
1!
1#
b000000000000000000001001 &
#2730000000
0!
0#
#2735000000
1!
1#
b000000000000000000001010 &
1'
#2740000000
0!
0#
#2745000000
1!
1"
1#
1$
b000000000000000000000000 &
0'
1(
#2750000000
0!
0#
#2755000000
1!
0"
1#
0$
b000000000000000000000001 &
0(
1)
#2760000000
0!
0#
#2765000000
1!
1#
b000000000000000000000010 &
0)
#2770000000
0!
0#
#2775000000
1!
1#
b000000000000000000000011 &
#2780000000
0!
0#
#2785000000
1!
1#
b000000000000000000000100 &
#2790000000
0!
0#
#2795000000
1!
1#
b000000000000000000000101 &
#2800000000
0!
0#
#2805000000
1!
1#
b000000000000000000000110 &
#2810000000
0!
0#
#2815000000
1!
1#
b000000000000000000000111 &
#2820000000
0!
0#
#2825000000
1!
1#
b000000000000000000001000 &
#2830000000
0!
0#
#2835000000
1!
1#
b000000000000000000001001 &
#2840000000
0!
0#
#2845000000
1!
1#
b000000000000000000001010 &
1'
#2850000000
0!
0#
#2855000000
1!
1"
1#
1$
b000000000000000000000000 &
0'
1(
#2860000000
0!
0#
#2865000000
1!
0"
1#
0$
b000000000000000000000001 &
0(
1)
#2870000000
0!
0#
#2875000000
1!
1#
b000000000000000000000010 &
0)
#2880000000
0!
0#
#2885000000
1!
1#
b000000000000000000000011 &
#2890000000
0!
0#
#2895000000
1!
1#
b000000000000000000000100 &
#2900000000
0!
0#
#2905000000
1!
1#
b000000000000000000000101 &
#2910000000
0!
0#
#2915000000
1!
1#
b000000000000000000000110 &
#2920000000
0!
0#
#2925000000
1!
1#
b000000000000000000000111 &
#2930000000
0!
0#
#2935000000
1!
1#
b000000000000000000001000 &
#2940000000
0!
0#
#2945000000
1!
1#
b000000000000000000001001 &
#2950000000
0!
0#
#2955000000
1!
1#
b000000000000000000001010 &
1'
#2960000000
0!
0#
#2965000000
1!
1"
1#
1$
b000000000000000000000000 &
0'
1(
#2970000000
0!
0#
#2975000000
1!
0"
1#
0$
b000000000000000000000001 &
0(
1)
#2980000000
0!
0#
#2985000000
1!
1#
b000000000000000000000010 &
0)
#2990000000
0!
0#
#2995000000
1!
1#
b000000000000000000000011 &
#3000000000
0!
0#
#3005000000
1!
1#
b000000000000000000000100 &
#3010000000
0!
0#
#3015000000
1!
1#
b000000000000000000000101 &
#3020000000
0!
0#
#3025000000
1!
1#
b000000000000000000000110 &
#3030000000
0!
0#
#3035000000
1!
1#
b000000000000000000000111 &
#3040000000
0!
0#
#3045000000
1!
1#
b000000000000000000001000 &
#3050000000
0!
0#
#3055000000
1!
1#
b000000000000000000001001 &
#3060000000
0!
0#
#3065000000
1!
1#
b000000000000000000001010 &
1'
#3070000000
0!
0#
#3075000000
1!
1"
1#
1$
b000000000000000000000000 &
0'
1(
#3080000000
0!
0#
#3085000000
1!
0"
1#
0$
b000000000000000000000001 &
0(
1)
#3090000000
0!
0#
#3095000000
1!
1#
b000000000000000000000010 &
0)
#3100000000
0!
0#
#3105000000
1!
1#
b000000000000000000000011 &
#3110000000
0!
0#
#3115000000
1!
1#
b000000000000000000000100 &
#3120000000
0!
0#
#3125000000
1!
1#
b000000000000000000000101 &
#3130000000
0!
0#
#3135000000
1!
1#
b000000000000000000000110 &
#3140000000
0!
0#
#3145000000
1!
1#
b000000000000000000000111 &
#3150000000
0!
0#
#3155000000
1!
1#
b000000000000000000001000 &
#3160000000
0!
0#
#3165000000
1!
1#
b000000000000000000001001 &
#3170000000
0!
0#
#3175000000
1!
1#
b000000000000000000001010 &
1'
#3180000000
0!
0#
#3185000000
1!
1"
1#
1$
b000000000000000000000000 &
0'
1(
#3190000000
0!
0#
#3195000000
1!
0"
1#
0$
b000000000000000000000001 &
0(
1)
#3200000000
0!
0#
#3205000000
1!
1#
b000000000000000000000010 &
0)
#3210000000
0!
0#
#3215000000
1!
1#
b000000000000000000000011 &
#3220000000
0!
0#
#3225000000
1!
1#
b000000000000000000000100 &
#3230000000
0!
0#
#3235000000
1!
1#
b000000000000000000000101 &
#3240000000
0!
0#
#3245000000
1!
1#
b000000000000000000000110 &
#3250000000
0!
0#
#3255000000
1!
1#
b000000000000000000000111 &
#3260000000
0!
0#
#3265000000
1!
1#
b000000000000000000001000 &
#3270000000
0!
0#
#3275000000
1!
1#
b000000000000000000001001 &
#3280000000
0!
0#
#3285000000
1!
1#
b000000000000000000001010 &
1'
#3290000000
0!
0#
#3295000000
1!
1"
1#
1$
b000000000000000000000000 &
0'
1(
#3300000000
0!
0#
#3305000000
1!
0"
1#
0$
b000000000000000000000001 &
0(
1)
#3310000000
0!
0#
#3315000000
1!
1#
b000000000000000000000010 &
0)
#3320000000
0!
0#
#3325000000
1!
1#
b000000000000000000000011 &
#3330000000
0!
0#
#3335000000
1!
1#
b000000000000000000000100 &
#3340000000
0!
0#
#3345000000
1!
1#
b000000000000000000000101 &
#3350000000
0!
0#
#3355000000
1!
1#
b000000000000000000000110 &
#3360000000
0!
0#
#3365000000
1!
1#
b000000000000000000000111 &
#3370000000
0!
0#
#3375000000
1!
1#
b000000000000000000001000 &
#3380000000
0!
0#
#3385000000
1!
1#
b000000000000000000001001 &
#3390000000
0!
0#
#3395000000
1!
1#
b000000000000000000001010 &
1'
#3400000000
0!
0#
#3405000000
1!
1"
1#
1$
b000000000000000000000000 &
0'
1(
#3410000000
0!
0#
#3415000000
1!
0"
1#
0$
b000000000000000000000001 &
0(
1)
#3420000000
0!
0#
#3425000000
1!
1#
b000000000000000000000010 &
0)
#3430000000
0!
0#
#3435000000
1!
1#
b000000000000000000000011 &
#3440000000
0!
0#
#3445000000
1!
1#
b000000000000000000000100 &
#3450000000
0!
0#
#3455000000
1!
1#
b000000000000000000000101 &
#3460000000
0!
0#
#3465000000
1!
1#
b000000000000000000000110 &
#3470000000
0!
0#
#3475000000
1!
1#
b000000000000000000000111 &
#3480000000
0!
0#
#3485000000
1!
1#
b000000000000000000001000 &
#3490000000
0!
0#
#3495000000
1!
1#
b000000000000000000001001 &
#3500000000
0!
0#
#3505000000
1!
1#
b000000000000000000001010 &
1'
#3510000000
0!
0#
#3515000000
1!
1"
1#
1$
b000000000000000000000000 &
0'
1(
#3520000000
0!
0#
#3525000000
1!
0"
1#
0$
b000000000000000000000001 &
0(
1)
#3530000000
0!
0#
#3535000000
1!
1#
b000000000000000000000010 &
0)
#3540000000
0!
0#
#3545000000
1!
1#
b000000000000000000000011 &
#3550000000
0!
0#
#3555000000
1!
1#
b000000000000000000000100 &
#3560000000
0!
0#
#3565000000
1!
1#
b000000000000000000000101 &
#3570000000
0!
0#
#3575000000
1!
1#
b000000000000000000000110 &
#3580000000
0!
0#
#3585000000
1!
1#
b000000000000000000000111 &
#3590000000
0!
0#
#3595000000
1!
1#
b000000000000000000001000 &
#3600000000
0!
0#
